ksp_time_tool/__init__.py
ksp_time_tool/common/__init__.py
ksp_time_tool/common/constants.py
ksp_time_tool/common/ksp_connection_manager.py
ksp_time_tool/common/ksp_dates.py
ksp_time_tool/common/met_time.py
ksp_time_tool/common/visitors.py
ksp_time_tool/pyqt_gui/__init__.py
ksp_time_tool/pyqt_gui/time_input_widgets.py
ksp_time_tool/pyqt_gui/tool_gui.py
ksp_time_tool/pyqt_gui/ut_seconds_edit.py
ksp_time_tool/test_cli/__init__.py
ksp_time_tool/test_cli/cli_converter.py
ksp_time_tool/test_cli/cli_handlers.py
ksp_time_tool-0.0.3.dist-info/METADATA
ksp_time_tool-0.0.3.dist-info/WHEEL
ksp_time_tool-0.0.3.dist-info/RECORD
