Metadata-Version: 2.4
Name: ksp_time_tool
Version: 0.0.3
Summary: KSP Time Tool - Tool for date conversion, alarms, and maneuver planning for Kerbal Space Program.
Project-URL: Homepage, https://github.com/aepereira/ksp-time-tool
Project-URL: Issues, https://github.com/aepereira/ksp-time-tool/issues
Author-email: "Arnaldo E. Pereira" <aepereira@gmail.com>
License: MIT
Classifier: Operating System :: OS Independent
Classifier: Programming Language :: Python :: 3
Requires-Python: >=3.8
Requires-Dist: krpc>=0.5.4
Requires-Dist: pyqt5<6.0.0,>=5.0.0
